[
  {
    "nom": "Xi Redmi Note10 5G",
    "description": "4 Go RAM – 128 Go\nÉcran 6,5\" FHD+ 90 Hz\nTriple caméra 48 MP\nBatterie 5000 mAh",
    "prix": 200,
    "image": "img/redmi_note10_5g.webp",
    "etat": "Reconditionné",
    "statut": "disponible",
    "badge": "🔥 Nouvelle génération",
    "contact": "tel:+33754372233",
    "paiement": "https://pay.sumup.com/b2c/XCDIASLRGV"
  },
  {
    "nom": "Xiaomi Redmi 15C",
    "description": "4 Go RAM – 128 Go\nÉcran 6,9\" – 120 Hz\nAppareil photo 50 MP\nBatterie longue durée",
    "prix": 180,
    "image": "img/redmi_15c_4g_noir.webp",
    "etat": "Neuf",
    "statut": "disponible",
    "badge": "🔥 Grand écran & autonomie",
    "contact": "tel:+33754372233",
    "paiement": "https://pay.sumup.com/b2c/XWQFKBH6T9"
  },
  {
    "nom": "Lenovo ThinkPad T490s",
    "description": "Intel Core i5-8365U\n16 Go RAM\nSSD 256 Go\nÉcran 14 pouces",
    "prix": 360,
    "image": "img/thinkpad_t490s_i5_8365u.webp",
    "etat": "Occasion",
    "statut": "disponible",
    "badge": "🔥 Windows 11 Pro",
    "contact": "tel:+33754372233",
    "paiement": "https://pay.sumup.com/b2c/XUZ1ECKGCK"
  },
  {
    "nom": "TCL 60 5G",
    "description": "256 Go – 6 Go RAM\nAndroid 15 – Processeur Dimensity 6300\nÉcran 6,7\" IPS – 120 Hz\nBatterie 5200 mAh\n\nGrade A – État proche du neuf.",
    "prix": 200,
    "image": "img/tcl_grade_a.webp",
    "etat": "Occasion Grade A",
    "statut": "disponible",
    "badge": "🔥 Grand écran & Autonomie",
    "contact": "tel:+33754372233",
    "paiement": "https://pay.sumup.com/b2c/X7WJL39FX2"
  },
  {
    "nom": "Samsung Galaxy A40",
    "description": "64 Go – 4 Go RAM\nÉcran Super AMOLED 5,9\" FHD+\nDouble caméra 16 + 5 Mpx\nCaméra avant 25 Mpx\nBatterie 3100 mAh\n\nGrade AB – Très bon.",
    "prix": 130,
    "image": "img/a40_a405_grade_ab_noir.webp",
    "etat": "Occasion Grade AB",
    "statut": "disponible",
    "badge": "🔥 Nouvelle technologie",
    "contact": "tel:+33754372233",
    "paiement": "https://pay.sumup.com/b2c/XR52P4U6MW"
  },
  {
    "nom": "Samsung Galaxy A16 4G",
    "description": "128 Go – Android 14\nSuper AMOLED 6,7\" – 90 Hz\nProcesseur Helio G99\nTriple caméra 50 + 5 + 2 Mpx\nBatterie 5000 mAh\n\nPack complet, Garantie 2 ans.",
    "prix": 190,
    "image": "img/Samsung_Galaxy_A16_4G_A165_128Go_EU_Bleu_Nuit.webp",
    "etat": "Neuf",
    "statut": "disponible",
    "badge": "🔥 S.AMOLED & Autonomie",
    "contact": "tel:+33754372233",
    "paiement": "https://pay.sumup.com/b2c/XRQAR4F9AC"
  }
]
